{"@context":"https://iiif.io/api/presentation/3/context.json","id":"https://vlsrobinson.github.io/VR_test_Canopy/api/facet/author/kim-sk-kyng-kim-sok-kyong.json","type":"Collection","label":{"none":["Kim Sŏk-kyŏng / Kim Sok-kyong"]},"items":[{"id":"https://cdm16786.contentdm.oclc.org/iiif/korean:24268/manifest.json","type":"Manifest","label":{"none":["Hyŏndae Munsu: kungmunhak posŭpsŏ (readings) / Hyondae Munsu: kungmunhak posupso"]},"thumbnail":[{"id":"https://cdm16786.contentdm.oclc.org/iiif/2/korean:24129/full/400,/0/default.jpg","type":"Image","format":"image/jpeg","width":400,"height":599}],"homepage":[{"id":"https://vlsrobinson.github.io/VR_test_Canopy/works/hyndae-munsu-kungmunhak-posps-readings-hyondae-munsu-kungmunhak-posupso","type":"Text","label":{"none":["Hyŏndae Munsu: kungmunhak posŭpsŏ (readings) / Hyondae Munsu: kungmunhak posupso"]}}]}],"partOf":[{"id":"https://vlsrobinson.github.io/VR_test_Canopy/api/facet/author.json","type":"Collection"}],"summary":{"none":["Author"]},"homepage":[{"id":"https://vlsrobinson.github.io/VR_test_Canopy/search?author=kim-sk-kyng-kim-sok-kyong","type":"Text","label":{"none":["Kim Sŏk-kyŏng / Kim Sok-kyong"]}}]}